netbox_config_backup/__init__.py
netbox_config_backup/choices.py
netbox_config_backup/filtersets.py
netbox_config_backup/forms.py
netbox_config_backup/git.py
netbox_config_backup/helpers.py
netbox_config_backup/navigation.py
netbox_config_backup/tables.py
netbox_config_backup/tasks.py
netbox_config_backup/template_content.py
netbox_config_backup/urls.py
netbox_config_backup/views.py
netbox_config_backup/api/__init__.py
netbox_config_backup/api/serializers.py
netbox_config_backup/api/urls.py
netbox_config_backup/api/views.py
netbox_config_backup/backup/__init__.py
netbox_config_backup/backup/processing.py
netbox_config_backup/exceptions/__init__.py
netbox_config_backup/graphql/__init__.py
netbox_config_backup/graphql/filters.py
netbox_config_backup/graphql/schema.py
netbox_config_backup/graphql/types.py
netbox_config_backup/jobs/__init__.py
netbox_config_backup/jobs/backup.py
netbox_config_backup/jobs/housekeeping.py
netbox_config_backup/management/__init__.py
netbox_config_backup/management/commands/__init__.py
netbox_config_backup/management/commands/fix_missing.py
netbox_config_backup/management/commands/listbackups.py
netbox_config_backup/management/commands/processbackup.py
netbox_config_backup/management/commands/rebuild.py
netbox_config_backup/management/commands/runbackup.py
netbox_config_backup/migrations/0001_initial.py
netbox_config_backup/migrations/0002_git_models.py
netbox_config_backup/migrations/0003_primary_model_to_bigid.py
netbox_config_backup/migrations/0004_custom_constraints.py
netbox_config_backup/migrations/0005_commit_add_time_field.py
netbox_config_backup/migrations/0006_backup_add_commit_last_time.py
netbox_config_backup/migrations/0007_backup_job_add_scheduled.py
netbox_config_backup/migrations/0008_backupjob_scheduled_nullable.py
netbox_config_backup/migrations/0009_bctc_file_model_backup_fk_restructure.py
netbox_config_backup/migrations/0010_backup_ip.py
netbox_config_backup/migrations/0011_alter_backup_name.py
netbox_config_backup-2.2.2.dist-info/licenses/LICENSE
netbox_config_backup-2.2.2.dist-info/METADATA
netbox_config_backup-2.2.2.dist-info/WHEEL
netbox_config_backup-2.2.2.dist-info/top_level.txt
netbox_config_backup-2.2.2.dist-info/RECORD
