Metadata-Version: 2.4
Name: netbox-config-backup
Version: 2.2.2
Summary: A NetBox Switch Configuration Backup Plugin
Author-email: Daniel Sheppard <dans@dansheps.com>
Maintainer-email: Daniel Sheppard <dans@dansheps.com>
License:                                  Apache License
Project-URL: Documentation, https://github.com/dansheps/netbox-config-backup/blob/main/README.md
Project-URL: Source, https://github.com/dansheps/netbox-config-backup
Project-URL: Tracker, https://github.com/dansheps/netbox-config-backup/issues
Keywords: netbox-plugin
Classifier: Programming Language :: Python :: 3
Requires-Python: >=3.12
License-File: LICENSE
Requires-Dist: netbox-napalm-plugin
Requires-Dist: netmiko>=4.0.0
Requires-Dist: napalm
Requires-Dist: uuid
Requires-Dist: dulwich
Requires-Dist: pydriller
Requires-Dist: deepdiff
Dynamic: license-file
